berserker/__init__.py
berserker/tokenization.py
berserker/transform.py
berserker/utils.py
berserker/assets/vocab.txt
berserker/ext/tokenization.py
basaka-0.2.1.dist-info/LICENSE
basaka-0.2.1.dist-info/METADATA
basaka-0.2.1.dist-info/WHEEL
basaka-0.2.1.dist-info/top_level.txt
basaka-0.2.1.dist-info/RECORD
