Metadata-Version: 2.1
Name: basaka
Version: 0.2.1
Summary: Berserker - BERt chineSE woRd toKenizER
Home-page: UNKNOWN
Author: Hoi
Author-email: hoiy927@gmail.com
License: UNKNOWN
Platform: UNKNOWN
Classifier: Programming Language :: Python :: 3
Classifier: License :: OSI Approved :: MIT License
Classifier: Operating System :: OS Independent
Requires-Dist: requests
Requires-Dist: six
Requires-Dist: tqdm
Requires-Dist: tensorflow (>=1.12.0)
